amp_depth_viz/.DS_Store
amp_depth_viz/__init__.py
amp_depth_viz/main.py
amp_depth_viz/sample/sample_input.bed
amp_depth_viz/sample/test_output.html
amp_depth_viz/template/template.html
amp_depth_viz-0.1.2.dist-info/METADATA
amp_depth_viz-0.1.2.dist-info/WHEEL
amp_depth_viz-0.1.2.dist-info/entry_points.txt
amp_depth_viz-0.1.2.dist-info/RECORD
